<?xml version="1.0" encoding="utf-8"?>
<TextureAtlas imagePath="EDGY XIAO LINE.png">
	<!-- Created with Adobe Animate version 18.0.1.115 -->
	<!-- http://www.adobe.com/products/animate.html -->
	<SubTexture name="edgy line0000" x="0" y="0" width="750" height="983" frameX="-129" frameY="0" frameWidth="879" frameHeight="983"/>
	<SubTexture name="edgy line0001" x="0" y="0" width="750" height="983" frameX="-129" frameY="0" frameWidth="879" frameHeight="983"/>
	<SubTexture name="edgy line0002" x="0" y="0" width="750" height="983" frameX="-129" frameY="0" frameWidth="879" frameHeight="983"/>
	<SubTexture name="edgy line0003" x="0" y="0" width="750" height="983" frameX="-129" frameY="0" frameWidth="879" frameHeight="983"/>
	<SubTexture name="edgy line0004" x="0" y="0" width="750" height="983" frameX="-129" frameY="0" frameWidth="879" frameHeight="983"/>
	<SubTexture name="edgy line0005" x="0" y="0" width="750" height="983" frameX="-129" frameY="0" frameWidth="879" frameHeight="983"/>
	<SubTexture name="edgy line0006" x="0" y="0" width="750" height="983" frameX="-129" frameY="0" frameWidth="879" frameHeight="983"/>
	<SubTexture name="edgy line0007" x="0" y="0" width="750" height="983" frameX="-129" frameY="0" frameWidth="879" frameHeight="983"/>
	<SubTexture name="edgy line0008" x="0" y="0" width="750" height="983" frameX="-129" frameY="0" frameWidth="879" frameHeight="983"/>
	<SubTexture name="edgy line0009" x="0" y="0" width="750" height="983" frameX="-129" frameY="0" frameWidth="879" frameHeight="983"/>
	<SubTexture name="edgy line0010" x="0" y="0" width="750" height="983" frameX="-129" frameY="0" frameWidth="879" frameHeight="983"/>
	<SubTexture name="edgy line0011" x="0" y="0" width="750" height="983" frameX="-129" frameY="0" frameWidth="879" frameHeight="983"/>
	<SubTexture name="edgy line0012" x="0" y="0" width="750" height="983" frameX="-129" frameY="0" frameWidth="879" frameHeight="983"/>
	<SubTexture name="edgy line0013" x="0" y="0" width="750" height="983" frameX="-129" frameY="0" frameWidth="879" frameHeight="983"/>
	<SubTexture name="edgy line0014" x="0" y="0" width="750" height="983" frameX="-129" frameY="0" frameWidth="879" frameHeight="983"/>
	<SubTexture name="edgy line0015" x="0" y="0" width="750" height="983" frameX="-129" frameY="0" frameWidth="879" frameHeight="983"/>
	<SubTexture name="edgy line0016" x="0" y="0" width="750" height="983" frameX="-129" frameY="0" frameWidth="879" frameHeight="983"/>
	<SubTexture name="edgy line0017" x="0" y="0" width="750" height="983" frameX="-129" frameY="0" frameWidth="879" frameHeight="983"/>
	<SubTexture name="edgy line0018" x="0" y="0" width="750" height="983" frameX="-129" frameY="0" frameWidth="879" frameHeight="983"/>
	<SubTexture name="edgy line0019" x="0" y="0" width="750" height="983" frameX="-129" frameY="0" frameWidth="879" frameHeight="983"/>
	<SubTexture name="edgy line0020" x="0" y="0" width="750" height="983" frameX="-129" frameY="0" frameWidth="879" frameHeight="983"/>
	<SubTexture name="edgy line0021" x="0" y="0" width="750" height="983" frameX="-129" frameY="0" frameWidth="879" frameHeight="983"/>
	<SubTexture name="edgy line0022" x="0" y="0" width="750" height="983" frameX="-129" frameY="0" frameWidth="879" frameHeight="983"/>
	<SubTexture name="edgy line0023" x="0" y="0" width="750" height="983" frameX="-129" frameY="0" frameWidth="879" frameHeight="983"/>
	<SubTexture name="edgy line0024" x="0" y="0" width="750" height="983" frameX="-129" frameY="0" frameWidth="879" frameHeight="983"/>
	<SubTexture name="edgy line0025" x="0" y="0" width="750" height="983" frameX="-129" frameY="0" frameWidth="879" frameHeight="983"/>
	<SubTexture name="edgy line0026" x="0" y="0" width="750" height="983" frameX="-129" frameY="0" frameWidth="879" frameHeight="983"/>
	<SubTexture name="edgy line0027" x="0" y="0" width="750" height="983" frameX="-129" frameY="0" frameWidth="879" frameHeight="983"/>
	<SubTexture name="edgy line0028" x="0" y="0" width="750" height="983" frameX="-129" frameY="0" frameWidth="879" frameHeight="983"/>
	<SubTexture name="edgy line0029" x="0" y="0" width="750" height="983" frameX="-129" frameY="0" frameWidth="879" frameHeight="983"/>
	<SubTexture name="edgy line0030" x="0" y="0" width="750" height="983" frameX="-129" frameY="0" frameWidth="879" frameHeight="983"/>
	<SubTexture name="edgy line0031" x="0" y="0" width="750" height="983" frameX="-129" frameY="0" frameWidth="879" frameHeight="983"/>
	<SubTexture name="edgy line0032" x="0" y="0" width="750" height="983" frameX="-129" frameY="0" frameWidth="879" frameHeight="983"/>
	<SubTexture name="edgy line0033" x="0" y="0" width="750" height="983" frameX="-129" frameY="0" frameWidth="879" frameHeight="983"/>
	<SubTexture name="edgy line0034" x="0" y="0" width="750" height="983" frameX="-129" frameY="0" frameWidth="879" frameHeight="983"/>
	<SubTexture name="edgy line0035" x="750" y="0" width="750" height="983" frameX="-129" frameY="0" frameWidth="879" frameHeight="983"/>
	<SubTexture name="edgy line0036" x="750" y="0" width="750" height="983" frameX="-129" frameY="0" frameWidth="879" frameHeight="983"/>
	<SubTexture name="edgy line0037" x="1500" y="0" width="750" height="983" frameX="-129" frameY="0" frameWidth="879" frameHeight="983"/>
	<SubTexture name="edgy line0038" x="2250" y="0" width="750" height="983" frameX="-129" frameY="0" frameWidth="879" frameHeight="983"/>
	<SubTexture name="edgy line0039" x="3000" y="0" width="750" height="983" frameX="-129" frameY="0" frameWidth="879" frameHeight="983"/>
	<SubTexture name="edgy line0040" x="0" y="983" width="750" height="983" frameX="-129" frameY="0" frameWidth="879" frameHeight="983"/>
	<SubTexture name="edgy line0041" x="750" y="983" width="879" height="983"/>
	<SubTexture name="edgy line0042" x="1629" y="983" width="750" height="983" frameX="-129" frameY="0" frameWidth="879" frameHeight="983"/>
	<SubTexture name="edgy line0043" x="2379" y="983" width="750" height="983" frameX="-129" frameY="0" frameWidth="879" frameHeight="983"/>
	<SubTexture name="edgy line0044" x="3129" y="983" width="750" height="983" frameX="-129" frameY="0" frameWidth="879" frameHeight="983"/>
	<SubTexture name="edgy line0045" x="0" y="1966" width="750" height="983" frameX="-129" frameY="0" frameWidth="879" frameHeight="983"/>
	<SubTexture name="edgy line0046" x="1629" y="983" width="750" height="983" frameX="-129" frameY="0" frameWidth="879" frameHeight="983"/>
	<SubTexture name="edgy line0047" x="2379" y="983" width="750" height="983" frameX="-129" frameY="0" frameWidth="879" frameHeight="983"/>
	<SubTexture name="edgy line0048" x="3129" y="983" width="750" height="983" frameX="-129" frameY="0" frameWidth="879" frameHeight="983"/>
	<SubTexture name="edgy line0049" x="0" y="1966" width="750" height="983" frameX="-129" frameY="0" frameWidth="879" frameHeight="983"/>
	<SubTexture name="edgy line0050" x="1629" y="983" width="750" height="983" frameX="-129" frameY="0" frameWidth="879" frameHeight="983"/>
	<SubTexture name="edgy line0051" x="2379" y="983" width="750" height="983" frameX="-129" frameY="0" frameWidth="879" frameHeight="983"/>
	<SubTexture name="edgy line0052" x="3129" y="983" width="750" height="983" frameX="-129" frameY="0" frameWidth="879" frameHeight="983"/>
	<SubTexture name="edgy line0053" x="0" y="1966" width="750" height="983" frameX="-129" frameY="0" frameWidth="879" frameHeight="983"/>
	<SubTexture name="edgy line0054" x="1629" y="983" width="750" height="983" frameX="-129" frameY="0" frameWidth="879" frameHeight="983"/>
	<SubTexture name="edgy line0055" x="2379" y="983" width="750" height="983" frameX="-129" frameY="0" frameWidth="879" frameHeight="983"/>
	<SubTexture name="edgy line0056" x="3129" y="983" width="750" height="983" frameX="-129" frameY="0" frameWidth="879" frameHeight="983"/>
	<SubTexture name="edgy line0057" x="0" y="1966" width="750" height="983" frameX="-129" frameY="0" frameWidth="879" frameHeight="983"/>
	<SubTexture name="edgy line0058" x="750" y="1966" width="750" height="983" frameX="-129" frameY="0" frameWidth="879" frameHeight="983"/>
	<SubTexture name="edgy line0059" x="1500" y="1966" width="750" height="983" frameX="-129" frameY="0" frameWidth="879" frameHeight="983"/>
	<SubTexture name="edgy line0060" x="2250" y="1966" width="750" height="983" frameX="-129" frameY="0" frameWidth="879" frameHeight="983"/>
	<SubTexture name="edgy line0061" x="3000" y="1966" width="750" height="983" frameX="-129" frameY="0" frameWidth="879" frameHeight="983"/>
	<SubTexture name="edgy line0062" x="0" y="2949" width="750" height="983" frameX="-129" frameY="0" frameWidth="879" frameHeight="983"/>
	<SubTexture name="edgy line0063" x="750" y="2949" width="750" height="983" frameX="-129" frameY="0" frameWidth="879" frameHeight="983"/>
	<SubTexture name="edgy line0064" x="1500" y="2949" width="750" height="983" frameX="-129" frameY="0" frameWidth="879" frameHeight="983"/>
	<SubTexture name="edgy line0065" x="2250" y="2949" width="750" height="983" frameX="-129" frameY="0" frameWidth="879" frameHeight="983"/>
	<SubTexture name="edgy line0066" x="3000" y="2949" width="750" height="983" frameX="-129" frameY="0" frameWidth="879" frameHeight="983"/>
	<SubTexture name="edgy line0067" x="0" y="3932" width="750" height="983" frameX="-129" frameY="0" frameWidth="879" frameHeight="983"/>
	<SubTexture name="edgy line0068" x="750" y="3932" width="750" height="983" frameX="-129" frameY="0" frameWidth="879" frameHeight="983"/>
	<SubTexture name="edgy line0069" x="1500" y="3932" width="750" height="983" frameX="-129" frameY="0" frameWidth="879" frameHeight="983"/>
	<SubTexture name="edgy line0070" x="2250" y="3932" width="750" height="983" frameX="-129" frameY="0" frameWidth="879" frameHeight="983"/>
	<SubTexture name="edgy line0071" x="3000" y="3932" width="750" height="983" frameX="-129" frameY="0" frameWidth="879" frameHeight="983"/>
	<SubTexture name="edgy line0072" x="0" y="4915" width="750" height="983" frameX="-129" frameY="0" frameWidth="879" frameHeight="983"/>
	<SubTexture name="edgy line0073" x="750" y="4915" width="750" height="983" frameX="-129" frameY="0" frameWidth="879" frameHeight="983"/>
	<SubTexture name="edgy line0074" x="1500" y="4915" width="750" height="983" frameX="-129" frameY="0" frameWidth="879" frameHeight="983"/>
	<SubTexture name="edgy line0075" x="2250" y="4915" width="750" height="983" frameX="-129" frameY="0" frameWidth="879" frameHeight="983"/>
	<SubTexture name="edgy line0076" x="3000" y="4915" width="750" height="983" frameX="-129" frameY="0" frameWidth="879" frameHeight="983"/>
	<SubTexture name="edgy line0077" x="0" y="5898" width="750" height="983" frameX="-129" frameY="0" frameWidth="879" frameHeight="983"/>
	<SubTexture name="edgy line0078" x="750" y="5898" width="750" height="983" frameX="-129" frameY="0" frameWidth="879" frameHeight="983"/>
	<SubTexture name="edgy line0079" x="1500" y="5898" width="750" height="983" frameX="-129" frameY="0" frameWidth="879" frameHeight="983"/>
	<SubTexture name="edgy line0080" x="2250" y="5898" width="750" height="983" frameX="-129" frameY="0" frameWidth="879" frameHeight="983"/>
	<SubTexture name="edgy line0081" x="3000" y="5898" width="750" height="983" frameX="-129" frameY="0" frameWidth="879" frameHeight="983"/>
	<SubTexture name="edgy line0082" x="0" y="6881" width="750" height="983" frameX="-129" frameY="0" frameWidth="879" frameHeight="983"/>
	<SubTexture name="edgy line0083" x="3000" y="2949" width="750" height="983" frameX="-129" frameY="0" frameWidth="879" frameHeight="983"/>
	<SubTexture name="edgy line0084" x="0" y="3932" width="750" height="983" frameX="-129" frameY="0" frameWidth="879" frameHeight="983"/>
	<SubTexture name="edgy line0085" x="750" y="3932" width="750" height="983" frameX="-129" frameY="0" frameWidth="879" frameHeight="983"/>
	<SubTexture name="edgy line0086" x="1500" y="3932" width="750" height="983" frameX="-129" frameY="0" frameWidth="879" frameHeight="983"/>
	<SubTexture name="edgy line0087" x="2250" y="3932" width="750" height="983" frameX="-129" frameY="0" frameWidth="879" frameHeight="983"/>
</TextureAtlas>
