{
	"animations": [
		{
			"offsets": [
				39,
				-7
			],
			"loop": false,
			"fps": 24,
			"anim": "singLEFT",
			"indices": [],
			"name": "Sayo Sing Note Right"
		},
		{
			"offsets": [
				-34,
				-44
			],
			"loop": false,
			"fps": 24,
			"anim": "singDOWN",
			"indices": [],
			"name": "Sayo Sing Note Down"
		},
		{
			"offsets": [
				-31,
				43
			],
			"loop": false,
			"fps": 24,
			"anim": "singUP",
			"indices": [],
			"name": "Sayo Sing Note Up"
		},
		{
			"offsets": [
				-63,
				1
			],
			"loop": false,
			"fps": 24,
			"anim": "singRIGHT",
			"indices": [],
			"name": "Sayo Sing Note Left"
		},
		{
			"offsets": [
				48,
				2
			],
			"loop": false,
			"fps": 24,
			"anim": "sad",
			"indices": [],
			"name": "Sayo Nara animated"
		},
		{
			"offsets": [
				1,
				0
			],
			"indices": [
				25,
				0,
				1,
				2,
				3,
				4,
				5,
				6,
				7,
				8,
				9,
				10,
				11,
				12
			],
			"fps": 24,
			"anim": "danceLeft",
			"loop": false,
			"name": "Sayo Idle nrw test"
		},
		{
			"offsets": [
				0,
				0
			],
			"indices": [
				13,
				14,
				15,
				16,
				17,
				18,
				19,
				20,
				21,
				22,
				23,
				24
			],
			"fps": 24,
			"anim": "danceRight",
			"loop": false,
			"name": "Sayo Idle nrw test"
		}
	],
	"no_antialiasing": false,
	"image": "characters/Doki_Sayo_Assets",
	"position": [
		30,
		45
	],
	"healthicon": "sayori",
	"flip_x": false,
	"healthbar_colors": [
		149,
		224,
		250
	],
	"camera_position": [
		100,
		30
	],
	"sing_duration": 6.1,
	"scale": 1
}